Planet_tools/__init__.py
Planet_tools/__version__.py
Planet_tools/calculate_param.py
Planet_tools/convert_param.py
Planet_tools/converter.py
Planet_tools/estimate_effect.py
Planet_tools/jwst.py
Planet_tools/phasecurve.py
Planet_tools/ring.py
Planet_tools/some_stats.py
Planet_tools/utils.py
Planet_tools/visibility.py
Planet_tools-0.4.0.dist-info/LICENSE
Planet_tools-0.4.0.dist-info/METADATA
Planet_tools-0.4.0.dist-info/WHEEL
Planet_tools-0.4.0.dist-info/top_level.txt
Planet_tools-0.4.0.dist-info/RECORD
