Metadata-Version: 2.1
Name: Planet-tools
Version: 0.4.0
Summary: Package with useful functions for exoplanetary research
Home-page: https://github.com/tundeakins/Planet_tools
Author: Babatunde Akinsanmi
Author-email: tunde.akinsanmi@astro.up.pt
License: UNKNOWN
Platform: UNKNOWN
Classifier: Programming Language :: Python
Classifier: License :: OSI Approved :: MIT License
Classifier: Operating System :: OS Independent
Provides-Extra: dev
Requires-Dist: pytest (>=3.7) ; extra == 'dev'
